<?xml version="1.0" encoding="UTF-8" standalone="no"?>
<databaseChangeLog
  xmlns="http://www.liquibase.org/xml/ns/dbchangelog"
  xmlns:ext="http://www.liquibase.org/xml/ns/dbchangelog-ext"
  xmlns:xsi="http://www.w3.org/2001/XMLSchema-instance"
  xsi:schemaLocation="http://www.liquibase.org/xml/ns/dbchangelog-ext
   http://www.liquibase.org/xml/ns/dbchangelog/dbchangelog-ext.xsd
   http://www.liquibase.org/xml/ns/dbchangelog
   http://www.liquibase.org/xml/ns/dbchangelog/dbchangelog-3.4.xsd">

  <changeSet id="post_comments-1" author="Dmitry">
    <insert tableName="post_comments">
      <column name="post_id" value="2"/>
      <column name="user_id" value="1"/>
      <column name="parent_id" value="1"/>
      <column name="time" value="2021-05-09 10:10:10"/>
      <column name="text" value="Нужно лучше искать, примеров полно"/>
    </insert>

    <insert tableName="post_comments">
      <column name="post_id" value="2"/>
      <column name="user_id" value="2"/>
      <column name="parent_id" value="1"/>
      <column name="time" value="2021-05-01 10:10:10"/>
      <column name="text" value="Зачет!"/>
    </insert>

    <insert tableName="post_comments">
      <column name="post_id" value="1"/>
      <column name="user_id" value="2"/>
      <column name="parent_id" value="2"/>
      <column name="time" value="2021-05-02 10:10:10"/>
      <column name="text" value="Кидай код, посмотрим."/>
    </insert>

    <insert tableName="post_comments">
      <column name="post_id" value="3"/>
      <column name="user_id" value="2"/>
      <column name="parent_id" value="1"/>
      <column name="time" value="2021-05-03 10:10:10"/>
      <column name="text" value="Давай код, подкорректируем"/>
    </insert>

    <insert tableName="post_comments">
      <column name="post_id" value="5"/>
      <column name="user_id" value="3"/>
      <column name="parent_id" value="1"/>
      <column name="time" value="2021-05-05 10:10:10"/>
      <column name="text" value="Используй класс Scanner"/>
    </insert>
  </changeSet>
</databaseChangeLog>
